{
    "status": "success",
    "message": "Record found.",
    "DataElement": {
        "publicId": "7063912",
        "version": "1",
        "longName": "ECOG - Performance Status Score",
        "shortName": "ECOG01",
        "definition": "The numerical score that represents the functional capabilities of a patient using the Eastern Cooperative Oncology Group Performance Status assessment.",
        "context": "NCI Standards",
        "origin": "NCI CRF Standards",
        "workflowStatus": "RELEASED",
        "registrationStatus": "Standard",
        "latestVersionIndicator": "Yes",
        "beginDate": "2019-11-22",
        "endDate": null,
        "changeDescription": "CDISC Aligned NCI Standard Template Text",
        "administrativeNotes": "5/4/23:classified and added CTDC ALTname for ECOG/DD. LS 2023/4/4: Added AQT for Alliance.wz",
        "unresolvedIssues": null,
        "deletedIndicator": "No",
        "createdBy": "HARTLEYG",
        "dateCreated": "2019-11-22",
        "modifiedBy": "SOKKERL",
        "dateModified": "2023-07-05",
        "DataElementConcept": {
            "publicId": "7063517",
            "version": "1",
            "longName": "Questionnaire Domain ECOG - Performance Status",
            "shortName": "6607890v1.0:7063515v1.0",
            "definition": "A subject domain utilized for the submission of information encompassing and representing data, vocabulary or records related to questionnaire._Eastern Cooperative Oncology Group (ECOG) Performance status.",
            "context": "NCI Standards",
            "origin": "NCI CRF Standards",
            "workflowStatus": "RELEASED",
            "registrationStatus": "Qualified",
            "latestVersionIndicator": "Yes",
            "beginDate": "2019-11-21",
            "endDate": null,
            "changeDescription": "Released. AK 2020-6-11; Created for CDSIC aligned NCI Standard CRFs. ghd",
            "administrativeNotes": null,
            "unresolvedIssues": null,
            "deletedIndicator": "No",
            "createdBy": "HARTLEYG",
            "dateCreated": "2019-11-21",
            "modifiedBy": "KUMMEROA",
            "dateModified": "2020-06-11",
            "ObjectClass": {
                "publicId": "6607890",
                "version": "1",
                "longName": "Questionnaire Domain",
                "shortName": "C49609",
                "definition": "A subject domain utilized for the submission of information encompassing and representing data, vocabulary or records related to questionnaire.",
                "context": "NCIP",
                "origin": "NCI Thesaurus",
                "workflowStatus": "RELEASED",
                "registrationStatus": "Application",
                "latestVersionIndicator": "Yes",
                "beginDate": "2019-01-10",
                "endDate": null,
                "changeDescription": null,
                "administrativeNotes": null,
                "unresolvedIssues": null,
                "deletedIndicator": "No",
                "createdBy": "TAYLORT",
                "dateCreated": "2019-01-10",
                "modifiedBy": "ONEDATA",
                "dateModified": "2019-01-10",
                "Concepts": [
                    {
                        "longName": "Questionnaire Domain",
                        "conceptCode": "C49609",
                        "definition": "A subject domain utilized for the submission of information encompassing and representing data, vocabulary or records related to questionnaire.",
                        "evsSource": "NCI_CONCEPT_CODE",
                        "primaryIndicator": "Yes",
                        "displayOrder": "0"
                    }
                ]
            },
            "Property": {
                "publicId": "7063515",
                "version": "1",
                "longName": "ECOG - Performance Status",
                "shortName": "C102408",
                "definition": "Eastern Cooperative Oncology Group (ECOG) Performance status.",
                "context": "NCIP",
                "origin": "NCI Thesaurus",
                "workflowStatus": "RELEASED",
                "registrationStatus": "Application",
                "latestVersionIndicator": "Yes",
                "beginDate": "2019-11-21",
                "endDate": null,
                "changeDescription": null,
                "administrativeNotes": null,
                "unresolvedIssues": null,
                "deletedIndicator": "No",
                "createdBy": "HARTLEYG",
                "dateCreated": "2019-11-21",
                "modifiedBy": "ONEDATA",
                "dateModified": "2019-11-21",
                "Concepts": [
                    {
                        "longName": "ECOG - Performance Status",
                        "conceptCode": "C102408",
                        "definition": "Eastern Cooperative Oncology Group (ECOG) Performance status.",
                        "evsSource": "NCI_CONCEPT_CODE",
                        "primaryIndicator": "Yes",
                        "displayOrder": "0"
                    }
                ]
            },
            "ConceptualDomain": {
                "publicId": "2435019",
                "version": "1",
                "longName": "Conceptual Entity",
                "shortName": "C20181",
                "definition": "An organizational header for concepts representing mostly abstract entities.",
                "context": "NCIP",
                "origin": "NCI Thesaurus",
                "workflowStatus": "RELEASED",
                "registrationStatus": "Application",
                "latestVersionIndicator": "Yes",
                "beginDate": "2005-12-06",
                "endDate": null,
                "changeDescription": null,
                "administrativeNotes": null,
                "unresolvedIssues": null,
                "deletedIndicator": "No",
                "createdBy": "CURTIST",
                "dateCreated": "2005-12-06",
                "modifiedBy": "SBR",
                "dateModified": "2006-12-20"
            }
        },
        "ValueDomain": {
            "publicId": "2015172",
            "version": "6",
            "longName": "Eastern Cooperative Oncology Group Scale",
            "shortName": "ECOG_SCALE",
            "definition": "the level of patient function scored using the modified ECOG performance status criteria.",
            "context": "CTEP",
            "type": "Enumerated",
            "dataType": "CHARACTER",
            "minLength": "1",
            "maxLength": "1",
            "minValue": null,
            "maxValue": null,
            "decimalPlace": null,
            "origin": null,
            "workflowStatus": "RELEASED",
            "registrationStatus": "Application",
            "latestVersionIndicator": "Yes",
            "beginDate": "2005-01-04",
            "endDate": null,
            "changeDescription": "New permissible values per CDUS.",
            "administrativeNotes": "5/24/23 Removed PV '0-1' per BMaeske. mr",
            "unresolvedIssues": null,
            "deletedIndicator": "No",
            "createdBy": "CAMPBELB",
            "dateCreated": "2005-01-04",
            "modifiedBy": "COLBERTM",
            "dateModified": "2023-05-24",
            "PermissibleValues": [
                {
                    "value": "0",
                    "valueDescription": "Fully active, able to carry on all pre-disease performance without restriction.",
                    "origin": null,
                    "beginDate": "2002-02-11",
                    "endDate": null,
                    "deletedIndicator": "No",
                    "createdBy": "CAMPBELB",
                    "dateCreated": "2005-01-04",
                    "modifiedBy": "SBR",
                    "dateModified": "2005-03-29",
                    "ValueMeaning": {
                        "publicId": "2572624",
                        "version": "1",
                        "longName": "Fully active, able to carry on all pre-disease performance without restriction.",
                        "shortName": "2572624",
                        "definition": "Fully active, able to carry on all pre-disease performance without restriction.",
                        "context": "NCIP",
                        "origin": null,
                        "workflowStatus": "RELEASED",
                        "registrationStatus": "Application",
                        "latestVersionIndicator": "Yes",
                        "beginDate": "2005-01-04",
                        "endDate": null,
                        "changeDescription": null,
                        "administrativeNotes": null,
                        "unresolvedIssues": null,
                        "deletedIndicator": "No",
                        "createdBy": "CAMPBELB",
                        "dateCreated": "2005-01-04",
                        "modifiedBy": "KUMMEROA",
                        "dateModified": "2022-07-25",
                        "Concepts": [
                            {
                                "longName": "ECOG Performance Status 0",
                                "conceptCode": "C105722",
                                "definition": "Fully active, able to carry on all pre-disease performance without restriction.",
                                "evsSource": "NCI_CONCEPT_CODE",
                                "primaryIndicator": "Yes",
                                "displayOrder": "0"
                            }
                        ]
                    }
                },
                {
                    "value": "1",
                    "valueDescription": "Restricted in physically strenuous activity but ambulatory and able to carry out work of a light or sedentary nature, e.g., light housework, office work.",
                    "origin": null,
                    "beginDate": "2002-02-11",
                    "endDate": null,
                    "deletedIndicator": "No",
                    "createdBy": "CAMPBELB",
                    "dateCreated": "2005-01-04",
                    "modifiedBy": "SBR",
                    "dateModified": "2005-03-29",
                    "ValueMeaning": {
                        "publicId": "2572286",
                        "version": "1",
                        "longName": "Restricted in physically strenuous activity but ambulatory and able to carry out work of a light or sedentary nature, e.g., light housework, office work.",
                        "shortName": "2572286",
                        "definition": "Restricted in physically strenuous activity but ambulatory and able to carry out work of a light or sedentary nature, e.g., light house work, office work.",
                        "context": "NCIP",
                        "origin": null,
                        "workflowStatus": "RELEASED",
                        "registrationStatus": "Application",
                        "latestVersionIndicator": "Yes",
                        "beginDate": "2004-12-02",
                        "endDate": null,
                        "changeDescription": null,
                        "administrativeNotes": null,
                        "unresolvedIssues": null,
                        "deletedIndicator": "No",
                        "createdBy": "CAMPBELB",
                        "dateCreated": "2004-12-02",
                        "modifiedBy": "KUMMEROA",
                        "dateModified": "2022-07-25",
                        "Concepts": [
                            {
                                "longName": "ECOG Performance Status 1",
                                "conceptCode": "C105723",
                                "definition": "Restricted in physically strenuous activity but ambulatory and able to carry out work of a light or sedentary nature, e.g., light house work, office work.",
                                "evsSource": "NCI_CONCEPT_CODE",
                                "primaryIndicator": "Yes",
                                "displayOrder": "0"
                            }
                        ]
                    }
                },
                {
                    "value": "2",
                    "valueDescription": "Ambulatory and capable of all selfcare but unable to carry out any work activities. Up and about more than 50% of waking hours.",
                    "origin": null,
                    "beginDate": "2002-02-11",
                    "endDate": null,
                    "deletedIndicator": "No",
                    "createdBy": "CAMPBELB",
                    "dateCreated": "2005-01-04",
                    "modifiedBy": "SBR",
                    "dateModified": "2005-03-29",
                    "ValueMeaning": {
                        "publicId": "2572287",
                        "version": "1",
                        "longName": "Ambulatory and capable of all selfcare but unable to carry out any work activities. Up and about more than 50% of waking hours.",
                        "shortName": "2572287",
                        "definition": "Ambulatory and capable of all self care but unable to carry out any work activities. Up and about more than 50% of waking hours.",
                        "context": "NCIP",
                        "origin": null,
                        "workflowStatus": "RELEASED",
                        "registrationStatus": "Application",
                        "latestVersionIndicator": "Yes",
                        "beginDate": "2004-12-02",
                        "endDate": null,
                        "changeDescription": null,
                        "administrativeNotes": null,
                        "unresolvedIssues": null,
                        "deletedIndicator": "No",
                        "createdBy": "CAMPBELB",
                        "dateCreated": "2004-12-02",
                        "modifiedBy": "GDEEN",
                        "dateModified": "2024-04-25",
                        "Concepts": [
                            {
                                "longName": "ECOG Performance Status 2",
                                "conceptCode": "C105725",
                                "definition": "Ambulatory and capable of all self care but unable to carry out any work activities. Up and about more than 50% of waking hours.",
                                "evsSource": "NCI_CONCEPT_CODE",
                                "primaryIndicator": "Yes",
                                "displayOrder": "0"
                            }
                        ]
                    }
                },
                {
                    "value": "3",
                    "valueDescription": "Capable of only limited selfcare, confined to bed or chair more than 50% of waking hours.",
                    "origin": null,
                    "beginDate": "2002-02-11",
                    "endDate": null,
                    "deletedIndicator": "No",
                    "createdBy": "CAMPBELB",
                    "dateCreated": "2005-01-04",
                    "modifiedBy": "SBR",
                    "dateModified": "2005-03-29",
                    "ValueMeaning": {
                        "publicId": "2572288",
                        "version": "1",
                        "longName": "Capable of only limited selfcare, confined to bed or chair more than 50% of waking hours.",
                        "shortName": "2572288",
                        "definition": "Capable of only limited selfcare, confined to bed or chair more than 50% of waking hours.",
                        "context": "NCIP",
                        "origin": null,
                        "workflowStatus": "RELEASED",
                        "registrationStatus": "Application",
                        "latestVersionIndicator": "Yes",
                        "beginDate": "2004-12-02",
                        "endDate": null,
                        "changeDescription": null,
                        "administrativeNotes": null,
                        "unresolvedIssues": null,
                        "deletedIndicator": "No",
                        "createdBy": "CAMPBELB",
                        "dateCreated": "2004-12-02",
                        "modifiedBy": "KUMMEROA",
                        "dateModified": "2022-07-25",
                        "Concepts": [
                            {
                                "longName": "ECOG Performance Status 3",
                                "conceptCode": "C105726",
                                "definition": "Capable of only limited selfcare, confined to bed or chair more than 50% of waking hours.",
                                "evsSource": "NCI_CONCEPT_CODE",
                                "primaryIndicator": "Yes",
                                "displayOrder": "0"
                            }
                        ]
                    }
                },
                {
                    "value": "4",
                    "valueDescription": "Completely disabled. Cannot carry on any selfcare. Totally confined to bed or chair.",
                    "origin": null,
                    "beginDate": "2002-02-11",
                    "endDate": null,
                    "deletedIndicator": "No",
                    "createdBy": "CAMPBELB",
                    "dateCreated": "2005-01-04",
                    "modifiedBy": "SBR",
                    "dateModified": "2005-03-29",
                    "ValueMeaning": {
                        "publicId": "2572289",
                        "version": "1",
                        "longName": "Completely disabled. Cannot carry on any selfcare. Totally confined to bed or chair.",
                        "shortName": "2572289",
                        "definition": "Completely disabled. Cannot carry on any selfcare. Totally confined to bed or chair.",
                        "context": "NCIP",
                        "origin": null,
                        "workflowStatus": "RELEASED",
                        "registrationStatus": "Application",
                        "latestVersionIndicator": "Yes",
                        "beginDate": "2004-12-02",
                        "endDate": null,
                        "changeDescription": null,
                        "administrativeNotes": null,
                        "unresolvedIssues": null,
                        "deletedIndicator": "No",
                        "createdBy": "CAMPBELB",
                        "dateCreated": "2004-12-02",
                        "modifiedBy": "GDEEN",
                        "dateModified": "2024-04-25",
                        "Concepts": [
                            {
                                "longName": "ECOG Performance Status 4",
                                "conceptCode": "C105727",
                                "definition": "Completely disabled. Cannot carry on any selfcare. Totally confined to bed or chair.",
                                "evsSource": "NCI_CONCEPT_CODE",
                                "primaryIndicator": "Yes",
                                "displayOrder": "0"
                            }
                        ]
                    }
                },
                {
                    "value": "5",
                    "valueDescription": "Dead",
                    "origin": null,
                    "beginDate": "2005-01-04",
                    "endDate": null,
                    "deletedIndicator": "No",
                    "createdBy": "CAMPBELB",
                    "dateCreated": "2005-01-04",
                    "modifiedBy": "SBR",
                    "dateModified": "2005-03-29",
                    "ValueMeaning": {
                        "publicId": "2570230",
                        "version": "1",
                        "longName": "Dead",
                        "shortName": "2570230",
                        "definition": "Dead.",
                        "context": "NCIP",
                        "origin": null,
                        "workflowStatus": "RELEASED",
                        "registrationStatus": "Application",
                        "latestVersionIndicator": "Yes",
                        "beginDate": "2004-06-21",
                        "endDate": null,
                        "changeDescription": "Added OBIB alternate name and identifier DWQ 03-21-2019",
                        "administrativeNotes": null,
                        "unresolvedIssues": null,
                        "deletedIndicator": "No",
                        "createdBy": "SBR",
                        "dateCreated": "2004-06-21",
                        "modifiedBy": "ZHANGWE",
                        "dateModified": "2022-03-24",
                        "Concepts": [
                            {
                                "longName": "Karnofsky Performance Status 0",
                                "conceptCode": "C105720",
                                "definition": "Dead.",
                                "evsSource": "NCI_CONCEPT_CODE",
                                "primaryIndicator": "Yes",
                                "displayOrder": "0"
                            }
                        ]
                    }
                }
            ],
            "ConceptualDomain": {
                "publicId": "2008556",
                "version": "1",
                "longName": "Assessment Results",
                "shortName": "ASSESS_RESULTS",
                "definition": "the results of evaluations of the patient and the patient's disease.",
                "context": "CTEP",
                "origin": null,
                "workflowStatus": "RELEASED",
                "registrationStatus": "Application",
                "latestVersionIndicator": "Yes",
                "beginDate": "2002-12-27",
                "endDate": null,
                "changeDescription": null,
                "administrativeNotes": null,
                "unresolvedIssues": null,
                "deletedIndicator": "No",
                "createdBy": "MSUPLEY",
                "dateCreated": "2002-12-27",
                "modifiedBy": "SBR",
                "dateModified": "2003-10-29"
            },
            "RepresentationTerm": {
                "publicId": "3623677",
                "version": "1",
                "longName": "Eastern Cooperative Oncology Group Scale",
                "shortName": "C25491:C25664",
                "definition": "The Eastern Cooperative Oncology Group (ECOG) was established in 1955. This is a cooperative group (Philadelphia, PA) funded primarily by the NCI, one of the largest clinical cancer research organizations in the US, incorporating universities, medical centers, Community Clinical Oncology Programs, and Cooperative Group Outreach Programs with almost 6000 physicians, nurses, pharmacists, statisticians, and clinical research associates from the US, Canada, and South Africa. ECOG has more than 90 active clinical trials in all types of adult malignancies. Annual accrual is 6,000 patients, with more than 20,000 patients in follow-up.:an ordered reference standard.",
                "context": "NCIP",
                "origin": null,
                "workflowStatus": "RELEASED",
                "registrationStatus": "Application",
                "latestVersionIndicator": "Yes",
                "beginDate": "2012-10-24",
                "endDate": null,
                "changeDescription": null,
                "administrativeNotes": null,
                "unresolvedIssues": null,
                "deletedIndicator": "No",
                "createdBy": "KRYSTKIA",
                "dateCreated": "2012-10-24",
                "modifiedBy": "ONEDATA",
                "dateModified": "2012-10-24",
                "Concepts": [
                    {
                        "longName": "Scale",
                        "conceptCode": "C25664",
                        "definition": "An ordered reference standard used to measure incremental changes.",
                        "evsSource": "NCI_CONCEPT_CODE",
                        "primaryIndicator": "Yes",
                        "displayOrder": "0"
                    },
                    {
                        "longName": "Eastern Cooperative Oncology Group",
                        "conceptCode": "C25491",
                        "definition": "A cooperative group funded primarily by the NCI, one of the largest clinical cancer research organizations in the US, incorporating universities, medical centers, Community Clinical Oncology Programs, and Cooperative Group Outreach Programs with almost 6000 physicians, nurses, pharmacists, statisticians, and clinical research associates from the US, Canada, and South Africa. ECOG has more than 90 active clinical trials in all types of adult malignancies. Annual accrual is 6,000 patients, with more than 20,000 patients in follow-up.",
                        "evsSource": "NCI_CONCEPT_CODE",
                        "primaryIndicator": "No",
                        "displayOrder": "1"
                    }
                ]
            }
        },
        "ClassificationSchemes": [
            {
                "publicId": "11518160",
                "version": "1",
                "longName": "CTDC (Clinical and Translational Data Commons)",
                "context": "CRDC",
                "ClassificationSchemeItems": [
                    {
                        "publicId": "13484614",
                        "version": "1",
                        "longName": "ECOG-ACRIN DD",
                        "context": "CRDC"
                    },
                    {
                        "publicId": "13484613",
                        "version": "1",
                        "longName": "MATCHBox",
                        "context": "CRDC"
                    }
                ]
            },
            {
                "publicId": "6921971",
                "version": "1",
                "longName": "CDISC Aligned Collection CDEs",
                "context": "NCI Standards",
                "ClassificationSchemeItems": [
                    {
                        "publicId": "7318430",
                        "version": "1",
                        "longName": "Vital Signs - CDISC Aligned",
                        "context": "NCI Standards"
                    }
                ]
            },
            {
                "publicId": "7434158",
                "version": "1",
                "longName": "CTEP CDISC Harmonization",
                "context": "CTEP",
                "ClassificationSchemeItems": [
                    {
                        "publicId": "7473989",
                        "version": "1",
                        "longName": "CTEP CDISC Vital Signs",
                        "context": "CTEP"
                    }
                ]
            },
            {
                "publicId": "7765162",
                "version": "1",
                "longName": "PMI CDISC Harmonization",
                "context": "PMI",
                "ClassificationSchemeItems": [
                    {
                        "publicId": "10882766",
                        "version": "1",
                        "longName": "PMI CDISC EC Template v1.0",
                        "context": "PMI"
                    }
                ]
            }
        ],
        "AlternateNames": [
            {
                "name": "CTEP",
                "type": "USED_BY",
                "context": "CTEP"
            },
            {
                "name": "COG",
                "type": "USED_BY",
                "context": "COG"
            },
            {
                "name": "SUPPQS_QVAL_QSECOG",
                "type": "COG GDE Short Name",
                "context": "COG"
            },
            {
                "name": "CCTG",
                "type": "USED_BY",
                "context": "CCTG"
            },
            {
                "name": "RS_RSORRES_ECOG101",
                "type": "OID, CCTG",
                "context": "CCTG"
            },
            {
                "name": "RS_RSORRES_ECOG101",
                "type": "Context Short Name",
                "context": "PMI"
            },
            {
                "name": "PS",
                "type": "CTDC Alt Name",
                "context": "CRDC"
            },
            {
                "name": "ecog_performance_status",
                "type": "CTDC Alt Name",
                "context": "CRDC"
            }
        ],
        "ReferenceDocuments": [
            {
                "documentName": "Performance Status (ECOG)",
                "documentText": "Performance Status (ECOG)",
                "documentType": "Preferred Question Text",
                "url": null,
                "context": "NCI Standards"
            },
            {
                "documentName": "CDISC Aligned NCI Standard Equivalent CDE",
                "documentText": "This data element is to be used for CDISC aligned data collection in place of CDE 88 from the original NCI Standard CRF Template.",
                "documentType": "CDISC Note",
                "url": null,
                "context": "NCI Standards"
            },
            {
                "documentName": "What was the ECOG performance status?",
                "documentText": "What was the ECOG performance status?",
                "documentType": "Alternate Question Text",
                "url": null,
                "context": "CTEP"
            },
            {
                "documentName": "ECOG performance status",
                "documentText": "ECOG performance status",
                "documentType": "Alternate Question Text",
                "url": null,
                "context": "CTEP"
            },
            {
                "documentName": "PMI - 1",
                "documentText": "ECOG performance status",
                "documentType": "Alternate Question Text",
                "url": null,
                "context": "PMI"
            },
            {
                "documentName": "PMI - 2",
                "documentText": "What was the ECOG performance status?",
                "documentType": "Alternate Question Text",
                "url": null,
                "context": "PMI"
            },
            {
                "documentName": "Alliance A092105",
                "documentText": "ECOG Score:",
                "documentType": "Alternate Question Text",
                "url": null,
                "context": "Alliance"
            }
        ]
    }
}
